compressai/_CXX.cpython-39-darwin.so
compressai/__init__.py
compressai/ans.cpython-39-darwin.so
compressai/version.py
compressai/datasets/__init__.py
compressai/datasets/cache.py
compressai/datasets/image.py
compressai/datasets/ndarray.py
compressai/datasets/pregenerated.py
compressai/datasets/rawvideo.py
compressai/datasets/stack.py
compressai/datasets/utils.py
compressai/datasets/video.py
compressai/datasets/vimeo90k.py
compressai/datasets/pointcloud/__init__.py
compressai/datasets/pointcloud/modelnet.py
compressai/datasets/pointcloud/s3dis.py
compressai/datasets/pointcloud/semantic_kitti.py
compressai/datasets/pointcloud/shapenet.py
compressai/entropy_models/__init__.py
compressai/entropy_models/entropy_models.py
compressai/entropy_models/entropy_models_vbr.py
compressai/latent_codecs/__init__.py
compressai/latent_codecs/base.py
compressai/latent_codecs/channel_groups.py
compressai/latent_codecs/checkerboard.py
compressai/latent_codecs/entropy_bottleneck.py
compressai/latent_codecs/gaussian_conditional.py
compressai/latent_codecs/hyper.py
compressai/latent_codecs/hyperprior.py
compressai/latent_codecs/rasterscan.py
compressai/latent_codecs/gain/__init__.py
compressai/latent_codecs/gain/hyper.py
compressai/latent_codecs/gain/hyperprior.py
compressai/layers/__init__.py
compressai/layers/basic.py
compressai/layers/gdn.py
compressai/layers/layers.py
compressai/layers/pointcloud/__init__.py
compressai/layers/pointcloud/hrtzxf2022.py
compressai/layers/pointcloud/pointnet.py
compressai/layers/pointcloud/pointnet2.py
compressai/layers/pointcloud/pointnet2_sfu.py
compressai/layers/pointcloud/utils.py
compressai/losses/__init__.py
compressai/losses/rate_distortion.py
compressai/losses/utils.py
compressai/losses/pointcloud/__init__.py
compressai/losses/pointcloud/chamfer.py
compressai/losses/pointcloud/hrtzxf2022.py
compressai/models/__init__.py
compressai/models/base.py
compressai/models/google.py
compressai/models/priors.py
compressai/models/sensetime.py
compressai-1.2.8.dist-info/licenses/LICENSE
compressai-1.2.8.dist-info/METADATA
compressai-1.2.8.dist-info/WHEEL
compressai-1.2.8.dist-info/top_level.txt
compressai-1.2.8.dist-info/RECORD
