Metadata-Version: 2.4
Name: compressai
Version: 1.2.8
Summary: A PyTorch library and evaluation platform for end-to-end compression research
Author-email: InterDigital AI Lab <compressai@interdigital.com>
License: BSD 3-Clause Clear License
Project-URL: Homepage, https://github.com/InterDigitalInc/CompressAI
Classifier: Development Status :: 3 - Alpha
Classifier: Intended Audience :: Developers
Classifier: Intended Audience :: Science/Research
Classifier: License :: OSI Approved :: BSD License
Classifier: Programming Language :: Python :: 3.8
Classifier: Programming Language :: Python :: 3.9
Classifier: Programming Language :: Python :: 3.10
Classifier: Programming Language :: Python :: 3.11
Classifier: Programming Language :: Python :: 3.12
Classifier: Topic :: Scientific/Engineering :: Artificial Intelligence
Requires-Python: >=3.8
License-File: LICENSE
Requires-Dist: einops
Requires-Dist: matplotlib
Requires-Dist: numpy<2.0,>=1.21.0
Requires-Dist: pandas
Requires-Dist: pybind11>=2.6.0
Requires-Dist: pytorch-msssim
Requires-Dist: scipy
Requires-Dist: setuptools>=68
Requires-Dist: tomli>=2.2.1
Requires-Dist: torch-geometric>=2.3.0
Requires-Dist: torch>=1.13.1
Requires-Dist: torchvision
Requires-Dist: tqdm
Requires-Dist: typing-extensions>=4.0.0
Requires-Dist: wheel>=0.32.0
Provides-Extra: test
Requires-Dist: plotly; extra == "test"
Requires-Dist: pytest; extra == "test"
Requires-Dist: pytest-cov; extra == "test"
Provides-Extra: dev
Requires-Dist: black; extra == "dev"
Requires-Dist: flake8; extra == "dev"
Requires-Dist: flake8-bugbear; extra == "dev"
Requires-Dist: flake8-comprehensions; extra == "dev"
Requires-Dist: isort; extra == "dev"
Requires-Dist: mypy; extra == "dev"
Requires-Dist: plotly; extra == "dev"
Requires-Dist: pytest; extra == "dev"
Requires-Dist: pytest-cov; extra == "dev"
Requires-Dist: ruff==0.8.6; extra == "dev"
Provides-Extra: doc
Requires-Dist: Jinja2<3.1; extra == "doc"
Requires-Dist: sphinx==4.3.0; extra == "doc"
Requires-Dist: sphinx-book-theme==1.0.1; extra == "doc"
Provides-Extra: tutorials
Requires-Dist: ipywidgets; extra == "tutorials"
Requires-Dist: jupyter; extra == "tutorials"
Provides-Extra: pointcloud
Requires-Dist: pyntcloud-yoda; extra == "pointcloud"
Dynamic: license-file
